{
  "cooker": "DynamicParser",
  "format": "json",
  "model": "com.stingray.qello.firetv.android.model.content.Content",
  "translator": "ContentTranslator",
  "modelType": "array",
  "query": "$.data[?(@.id in [$$par0$$])].data[?(@.id)]",
  "matchList": [
    "data/title@mTitle",
    "data/artists@mSubtitle",
    "id@mId",
    "data_type@mAssetType",
    "data/short_description@mDescription",
    "data/images/0/url@mUrl",
    "data/images/0/url@mCardImageUrl",
    "data/images/1/url@mBackgroundImageUrl",
    "id@mChannelId"
  ]
}